lazycluster/__init__.py
lazycluster/_about.py
lazycluster/_utils.py
lazycluster/exceptions.py
lazycluster/runtime_mgmt.py
lazycluster/runtimes.py
lazycluster/settings.py
lazycluster/utils.py
lazycluster/cluster/__init__.py
lazycluster/cluster/dask_cluster.py
lazycluster/cluster/exceptions.py
lazycluster/cluster/hyperopt_cluster.py
lazycluster/cluster/runtime_cluster.py
lazycluster/scripts/__init__.py
lazycluster/scripts/cli_handler.py
lazycluster-0.2.4.dist-info/LICENSE
lazycluster-0.2.4.dist-info/METADATA
lazycluster-0.2.4.dist-info/WHEEL
lazycluster-0.2.4.dist-info/top_level.txt
lazycluster-0.2.4.dist-info/RECORD
