Metadata-Version: 2.1
Name: lazycluster
Version: 0.2.4
Summary: Distributed machine learning made simple.
Home-page: https://github.com/ml-tooling/lazycluster.git
Author: ML Tooling Team
Author-email: team@mltooling.org
License: Apache License 2.0
Project-URL: Changelog, https://github.com/ml-tooling/lazycluster.git/releases
Project-URL: Issue Tracker, https://github.com/ml-tooling/lazycluster.git/issues
Project-URL: Documentation, https://github.com/ml-tooling/lazycluster.git#documentation
Project-URL: Source, https://github.com/ml-tooling/lazycluster.git
Platform: UNKNOWN
Classifier: Development Status :: 4 - Beta
Classifier: Intended Audience :: Developers
Classifier: Intended Audience :: Science/Research
Classifier: License :: OSI Approved :: MIT License
Classifier: Natural Language :: English
Classifier: Operating System :: OS Independent
Classifier: Programming Language :: Python :: 3 :: Only
Classifier: Programming Language :: Python :: 3
Classifier: Programming Language :: Python :: 3.6
Classifier: Programming Language :: Python :: 3.7
Classifier: Programming Language :: Python :: 3.8
Classifier: Programming Language :: Python :: 3.9
Classifier: Programming Language :: Python :: Implementation :: PyPy
Classifier: Programming Language :: Python :: Implementation :: CPython
Classifier: Topic :: Software Development :: Libraries
Classifier: Topic :: Software Development :: Libraries :: Python Modules
Classifier: Topic :: Scientific/Engineering :: Artificial Intelligence
Requires-Python: >=3.6
Requires-Dist: fabric
Requires-Dist: stormssh
Requires-Dist: cloudpickle
Requires-Dist: psutil
Requires-Dist: click-spinner
Provides-Extra: dev
Requires-Dist: setuptools ; extra == 'dev'
Requires-Dist: wheel ; extra == 'dev'
Requires-Dist: twine ; extra == 'dev'
Requires-Dist: flake8 ; extra == 'dev'
Requires-Dist: pytest ; extra == 'dev'
Requires-Dist: pytest-mock ; extra == 'dev'
Requires-Dist: mypy ; extra == 'dev'
Requires-Dist: pytest-cov ; extra == 'dev'
Requires-Dist: black ; extra == 'dev'
Requires-Dist: pydocstyle ; extra == 'dev'
Requires-Dist: isort ; extra == 'dev'
Requires-Dist: lazydocs ; extra == 'dev'
Requires-Dist: distributed ; extra == 'dev'
Requires-Dist: hyperopt ; extra == 'dev'
Requires-Dist: docker ; extra == 'dev'
